{"primaryImpact":{"impactArea":[],"impactTypeComp":"000000000000010000","impactWayOfAssigning":"0000000","targetTypeId":"0001100011000","impactTypeId":"000000000000000","turnsToBeActivated":0,"turnsActive":0,"isPositiveImpact":false,"buff":false,"holyBuff":false,"powerBuff":false,"poisonBuff":false,"weaknessBuff":false,"stunBuff":false,"disarmBuff":false,"manaChange":false,"healthChange":false,"damageChange":false,"passive":false,"continues":false,"permanent":false,"cellImpact":false,"fireCell":false,"holyCell":false,"poisonCell":false,"dispel":false,"isBuffDispel":false,"isAllPositiveDispel":false,"impactQuantity":0},"manaCost":9,"name":"Kings Guard","cost":1750,"cardID":"","collectionID":"","description":"kills one random minion in adjacent cell of hero"}