{"onSpawnImpact":null,"onDeathImpact":null,"onDefendImpact":null,"onAttackImpact":null,"onComboImpact":null,"secondaryImpact":null,"health":9,"isAlive":false,"cardCell":null,"damage":5,"impactsAppliedToThisOne":null,"didMoveInThisTurn":false,"didAttackInThisTurn":false,"moveRange":0,"minAttackRange":0,"maxAttackRange":4,"isMelee":false,"isRanged":true,"isHybrid":false,"isComboAttacker":false,"buffHealthChange":0,"buffDamageChange":0,"manaCost":5,"name":"FireBreathing Dragon","cell":null,"cost":250,"match":null,"player":null,"cardID":null,"description":""}