{"health":6,"isAlive":false,"damage":1,"impactsAppliedToThisOne":[],"didMoveInThisTurn":false,"didAttackInThisTurn":false,"moveRange":2,"minAttackRange":0,"maxAttackRange":0,"isMelee":true,"isRanged":false,"isHybrid":false,"onAttackImpact":{"impactEffectComp":{"impactTypeIdComp":"000000000","impactWayOfAssigning":"0000","impactQuantity":0,"impactArea":[],"doesHaveAntiHolyBuff":false,"doesHaveHolyBuffCanceler":false,"doesHaveAntiNegativeImpact":false,"doesHaveAntiPoison":false,"killIt":false,"doesHaveAntiDisarm":false,"doesHaveRisingDamage":false,"difRisingDamage":false,"immuneToMinDamage":false,"putItOnDefend":false,"putItOnAttack":false,"putItOnDyingWish":false,"putItOnSummonImpact":false},"impactArea":[],"impactAreaClass":{"targetTypeId":"0001200000000","impactArea":[],"isSelectedCellImportant":false,"validOnAll":false,"validOnAWholeTeam":false,"validOnFriendlyTeamOnly":false,"validOnHostileTeamOnly":false,"isImpactAreaSquare":false,"oneColumn":false,"oneSoldierBeside":false,"allSoldiersBeside":false,"allSoldierType":false,"minionSoldierTypeOnly":false,"oneRandomClosest":false,"isRandom":false,"oneRow":false,"isRangedSetting":false,"plusItSelf":false,"hybridTypeMatters":false,"rangedTypeMatters":false,"meleeTypeMatters":false,"targetAttackTypeMatters":false,"squareLength":0,"distance":0},"impactTypeComp":"000000000","impactWayOfAssigning":"0000","targetTypeId":"0001200000000","impactTypeId":"0020060100000","turnsToBeActivated":0,"turnsActive":0,"isPositiveImpact":false,"buff":false,"holyBuff":false,"powerBuff":false,"poisonBuff":false,"weaknessBuff":false,"stunBuff":false,"disarmBuff":false,"manaChange":false,"healthChange":false,"damageChange":false,"passive":false,"continues":false,"permanent":false,"cellImpact":false,"fireCell":false,"holyCell":false,"poisonCell":false,"dispel":false,"isBuffDispel":false,"isAllPositiveDispel":false,"impactQuantity":0},"isComboAttacker":false,"dispelableHealthChange":0,"dispelableDamageChange":0,"previousTargets":{},"manaCost":3,"name":"The Wolf","cost":400,"cardID":"","collectionID":"","description":"like the leopard but with 6 ap"}